examples/__init__.py
examples/app/__init__.py
examples/app/cli.py
md_click/__init__.py
md_click/main.py
tests/__init__.py
tests/test_main.py
md_click-1.0.1.dist-info/LICENSE
md_click-1.0.1.dist-info/METADATA
md_click-1.0.1.dist-info/WHEEL
md_click-1.0.1.dist-info/entry_points.txt
md_click-1.0.1.dist-info/top_level.txt
md_click-1.0.1.dist-info/zip-safe
md_click-1.0.1.dist-info/RECORD
