Metadata-Version: 2.1
Name: md-click
Version: 1.0.1
Summary: A command line tool for automatically generating .md files from click's CLI command.
Home-page: https://github.com/RiveryIo/md-click
Author: Rivery
License: BSD 3.0
Project-URL: Bug Tracker, https://github.com/RiveryIo/md-click/issues
Platform: UNKNOWN
Classifier: Development Status :: 5 - Production/Stable
Classifier: Topic :: Documentation
Classifier: License :: OSI Approved :: BSD License
Classifier: Topic :: Software Development :: Documentation
Classifier: Topic :: Software Development :: Build Tools
Classifier: Topic :: Software Development :: Libraries :: Python Modules
Classifier: Topic :: Text Processing :: Markup :: Markdown
Requires-Dist: click (<=7.1.2,>=7.0.0)
